{
  "Footer": {
    "description": "Auto imported from components/Footer.vue"
  },
  "Header": {
    "description": "Auto imported from components/Header.vue"
  },
  "BlogItem1": {
    "description": "Auto imported from components/blog/BlogItem1.vue"
  },
  "BlogItem2": {
    "description": "Auto imported from components/blog/BlogItem2.vue"
  },
  "BlogItem3": {
    "description": "Auto imported from components/blog/BlogItem3.vue"
  },
  "BlogSidebar": {
    "description": "Auto imported from components/blog/BlogSidebar.vue"
  },
  "BlogSidebar2": {
    "description": "Auto imported from components/blog/BlogSidebar2.vue"
  },
  "ProductBox1": {
    "description": "Auto imported from components/product-box/ProductBox1.vue"
  },
  "ProductBox2": {
    "description": "Auto imported from components/product-box/ProductBox2.vue"
  },
  "ProductBox3": {
    "description": "Auto imported from components/product-box/ProductBox3.vue"
  },
  "ProductBox4": {
    "description": "Auto imported from components/product-box/ProductBox4.vue"
  },
  "ProductBox5": {
    "description": "Auto imported from components/product-box/ProductBox5.vue"
  },
  "WidgetsRelatedProducts": {
    "description": "Auto imported from components/widgets/RelatedProducts.vue"
  },
  "WidgetsShopSidebar": {
    "description": "Auto imported from components/widgets/ShopSidebar.vue"
  },
  "WidgetsTimer": {
    "description": "Auto imported from components/widgets/Timer.vue"
  },
  "InstagramArea": {
    "description": "Auto imported from components/instagram/InstagramArea.vue"
  },
  "InstagramAreaElectronics": {
    "description": "Auto imported from components/instagram/InstagramAreaElectronics.vue"
  },
  "InstagramAreaFurniture": {
    "description": "Auto imported from components/instagram/InstagramAreaFurniture.vue"
  },
  "InstagramSliderItem": {
    "description": "Auto imported from components/instagram/InstagramSliderItem.vue"
  }
}
